.gitignore
LICENSE
README.md
__main__.py
requirements.txt
setup.py
.github/workflows/release.yml
discotool/__init__.py
discotool/__main__.py
discotool/_version.py
discotool/discotool.py
discotool.egg-info/PKG-INFO
discotool.egg-info/SOURCES.txt
discotool.egg-info/dependency_links.txt
discotool.egg-info/entry_points.txt
discotool.egg-info/requires.txt
discotool.egg-info/top_level.txt
discotool/usbinfos/__init__.py
discotool/usbinfos/pyserial_list_ports_osx.py
discotool/usbinfos/pyserial_list_ports_windows.py
discotool/usbinfos/usb_descriptor_win32.py
discotool/usbinfos/usbinfos_common.py
discotool/usbinfos/usbinfos_linux.py
discotool/usbinfos/usbinfos_macos.py
discotool/usbinfos/usbinfos_win32.py
docs/circup_to_clue.png
docs/circup_update_clue.png
docs/examples.md
docs/list_clue.png
docs/list_clue_qt_s2.png
docs/list_clue_ttgo_tiny.png
docs/list_qt_trinkey_huzzah32.png
docs/list_tiny_nano_esp32.png
docs/repl_to_clue.png
examples/find_boards_by_volume.py
examples/find_boards_with_filters.py
examples/install_uf2.py
examples/macos_terminal_open_tabs.py
tests/locations.py
tests/simpletest.py
tools/build.sh
tools/build_help.py
tools/build_local.sh